Metadata-Version: 2.1
Name: taosc
Version: 2.0.3
Summary: TDengine python client package
Home-page: https://github.com/pypa/sampleproject
Author: Taosdata Inc.
Author-email: support@taosdata.com
License: UNKNOWN
Platform: UNKNOWN
Classifier: Programming Language :: Python :: 3
